nameko_zipkin/__init__.py
nameko_zipkin/constants.py
nameko_zipkin/method_proxy.py
nameko_zipkin/provider.py
nameko_zipkin/transport.py
nameko_zipkin/utils.py
emplo_nameko_zipkin-0.1.8.dist-info/LICENSE
emplo_nameko_zipkin-0.1.8.dist-info/METADATA
emplo_nameko_zipkin-0.1.8.dist-info/WHEEL
emplo_nameko_zipkin-0.1.8.dist-info/top_level.txt
emplo_nameko_zipkin-0.1.8.dist-info/RECORD
