Metadata-Version: 2.1
Name: emplo-nameko-zipkin
Version: 0.1.8
Summary: Zipkin tracing for nameko framework
Home-page: https://github.com/Emplocity/nameko-zipkin
Author: Maxim Kiyan <maxim.k@fraglab.com>, Zbigniew Siciarz <zbigniew.siciarz@emplocity.pl>
License: UNKNOWN
Platform: UNKNOWN
License-File: LICENSE
Requires-Dist: py-zipkin (>=0.20.2)
Requires-Dist: nameko (>=2.14.0)
